calculadora/__init__.py
calculadora/__main__.py
calculadora/operaciones/__init__.py
calculadora/operaciones/aditivas.py
calculadora/operaciones/multiplicativas/multiplicativas.py
calculadora/utils/__init__.py
calculadora/utils/fraccion.py
calculadoras-0.1.0.dist-info/METADATA
calculadoras-0.1.0.dist-info/WHEEL
calculadoras-0.1.0.dist-info/RECORD
