Metadata-Version: 2.1
Name: calculadoras
Version: 0.1.0
Summary: Calculadora par aoperaciones basicas
License: MIT
Author: Andre
Requires-Python: >=3.11.1,<3.13
Classifier: License :: OSI Approved :: MIT License
Classifier: Programming Language :: Python :: 3
Requires-Dist: pandas (>=2.1.1,<3.0.0)
